torch_module_monitor/__init__.py
torch_module_monitor/attention.py
torch_module_monitor/hooks.py
torch_module_monitor/monitor.py
torch_module_monitor/py.typed
torch_module_monitor/refined_coordinate_check.py
torch_module_monitor/storage.py
torch_module_monitor-0.1.0.dist-info/licenses/LICENSE
torch_module_monitor-0.1.0.dist-info/METADATA
torch_module_monitor-0.1.0.dist-info/WHEEL
torch_module_monitor-0.1.0.dist-info/top_level.txt
torch_module_monitor-0.1.0.dist-info/RECORD
