Metadata-Version: 2.4
Name: torch-module-monitor
Version: 0.1.0
Summary: Diagnostics for PyTorch model training - monitor activations, parameters, and gradients
Author-email: Sebastian Bordt <sbordt@posteo.de>
License: MIT License
Project-URL: Homepage, https://github.com/tml-tuebingen/torch-module-monitor
Project-URL: Source, https://github.com/tml-tuebingen/torch-module-monitor
Project-URL: Issues, https://github.com/tml-tuebingen/torch-module-monitor/issues
Project-URL: Documentation, https://torch-module-monitor.readthedocs.io
Keywords: pytorch,deep-learning,diagnostics,monitoring,training,mup,coordinate-check,activations,gradients
Classifier: Development Status :: 3 - Alpha
Classifier: Intended Audience :: Science/Research
Classifier: Intended Audience :: Developers
Classifier: Topic :: Scientific/Engineering :: Artificial Intelligence
Classifier: Topic :: Software Development :: Libraries :: Python Modules
Classifier: License :: OSI Approved :: MIT License
Classifier: Programming Language :: Python :: 3
Classifier: Programming Language :: Python :: 3.9
Classifier: Programming Language :: Python :: 3.10
Classifier: Programming Language :: Python :: 3.11
Classifier: Programming Language :: Python :: 3.12
Requires-Python: >=3.9
License-File: LICENSE
Requires-Dist: torch>=2.1
Requires-Dist: numpy>=1.24
Requires-Dist: h5py>=3.8
Provides-Extra: wandb
Requires-Dist: wandb>=0.16; extra == "wandb"
Provides-Extra: tb
Requires-Dist: tensorboard>=2.15; extra == "tb"
Provides-Extra: dev
Requires-Dist: pytest>=8.2; extra == "dev"
Requires-Dist: pytest-xdist>=3.6; extra == "dev"
Requires-Dist: pre-commit>=3.7; extra == "dev"
Requires-Dist: black>=24.3; extra == "dev"
Requires-Dist: flake8>=7.0; extra == "dev"
Requires-Dist: mypy>=1.10; extra == "dev"
Requires-Dist: sphinx>=7.2; extra == "dev"
Requires-Dist: sphinx-autoapi>=3.1; extra == "dev"
Dynamic: license-file
